dynamic_default_args/__init__.py
dynamic_default_args/_version.py
dynamic_default_args/dynamic_default_args.py
dynamic_default_args/event.py
dynamic_default_args/format_dict.py
dynamic_default_args-0.0.6.dist-info/LICENSE.txt
dynamic_default_args-0.0.6.dist-info/METADATA
dynamic_default_args-0.0.6.dist-info/WHEEL
dynamic_default_args-0.0.6.dist-info/top_level.txt
dynamic_default_args-0.0.6.dist-info/RECORD
