Metadata-Version: 2.1
Name: dynamic-default-args
Version: 0.0.6
Summary: Python dynamic default arguments.
Home-page: https://github.com/inspiros/dynamic-default-args
Author: Hoang-Nhat Tran (inspiros)
Author-email: hnhat.tran@gmail.com
License: MIT-0
Project-URL: Source, https://github.com/inspiros/dynamic-default-args
Keywords: dynamic-default-args
Classifier: Development Status :: 3 - Alpha
Classifier: Intended Audience :: Developers
Classifier: License :: OSI Approved :: MIT No Attribution License (MIT-0)
Classifier: Programming Language :: Python
Classifier: Programming Language :: Python :: 3
Classifier: Operating System :: OS Independent
Classifier: Topic :: Scientific/Engineering
Requires-Python: >=3
License-File: LICENSE.txt
